pyeth/__init__.py
pyeth/class_web3.py
pyeth/class_web3_local.py
yongshi_pyeth-0.1.4.dist-info/LICENSE
yongshi_pyeth-0.1.4.dist-info/METADATA
yongshi_pyeth-0.1.4.dist-info/WHEEL
yongshi_pyeth-0.1.4.dist-info/top_level.txt
yongshi_pyeth-0.1.4.dist-info/RECORD
