Metadata-Version: 2.1
Name: yongshi-pyeth
Version: 0.1.4
Summary: A python library for web3 eth
Home-page: https://github.com/Michael-Yongshi/Py-Library-Eth
Author: Michael-Yongshi
Author-email: 4registration@outlook.com
License: UNKNOWN
Platform: UNKNOWN
Classifier: Programming Language :: Python :: 3
Classifier: License :: OSI Approved :: GNU General Public License v3 or later (GPLv3+)
Classifier: Operating System :: OS Independent
Requires-Python: >=3.5
